quickdriver/__init__.py
quickdriver/quickdriver.py
quickdriver-2.0.0.dist-info/licenses/LICENSE
quickdriver-2.0.0.dist-info/WHEEL
quickdriver-2.0.0.dist-info/METADATA
quickdriver-2.0.0.dist-info/RECORD
