Metadata-Version: 2.4
Name: quickdriver
Version: 2.0.0
Summary: A wrapper for Selenium WebDriver that simplifies browser automation.
Keywords: selenium
Author-email: nishizawatakamasa <nszw0502@gmail.com>
Requires-Python: >=3.8
License-Expression: MIT
Classifier: Programming Language :: Python :: 3
Classifier: Operating System :: OS Independent
License-File: LICENSE
Requires-Dist: selenium >= 4.27.1
Requires-Dist: pandas >= 2.2.3
Requires-Dist: tqdm >= 4.67.1
Requires-Dist: pyarrow >= 16.1.0
Project-URL: repository, https://github.com/nishizawatakamasa/quickdriver
